docs/source/conf.py
docs/source/foreground.rst
docs/source/index.rst
docs/source/mflike.rst
docs/source/_static/logo.png
docs/source/_static/css/custom.css
docs/source/notebooks/Makefile
docs/source/notebooks/tutorial_fisher.ipynb
docs/source/notebooks/tutorial_foregrounds.ipynb
docs/source/notebooks/tutorial_loading.ipynb
docs/source/notebooks/tutorial_logp_value.ipynb
docs/source/notebooks/tutorial_residuals.ipynb
examples/mflike_example.yaml
mflike/EE.yaml
mflike/Foreground.yaml
mflike/TE.yaml
mflike/TEEE.yaml
mflike/TT.yaml
mflike/TTEE.yaml
mflike/TTTE.yaml
mflike/TTTEEE.yaml
mflike/_MFLike.yaml
mflike/__init__.py
mflike/_version.py
mflike/calib_E.yaml
mflike/calib_T.yaml
mflike/fg_EE.yaml
mflike/fg_TE.yaml
mflike/fg_TT.yaml
mflike/foreground.py
mflike/mflike.py
mflike/mflike_common.yaml
mflike/tests/test_mflike.py
mflike-1.0.2.dist-info/licenses/LICENSE
scripts/generate_beams_w_bandpass_shifts.py
mflike-1.0.2.dist-info/METADATA
mflike-1.0.2.dist-info/WHEEL
mflike-1.0.2.dist-info/top_level.txt
mflike-1.0.2.dist-info/RECORD
