Metadata-Version: 2.4
Name: mflike
Version: 1.0.2
Summary: SO LAT multi-frequency likelihood for cobaya
Author: Simons Observatory Collaboration Power Spectrum Group aka so_ps 1 & 2
License: 
Project-URL: Homepage, https://github.com/simonsobs/LAT_MFLike
Project-URL: Documentation, https://lat-mflike.readthedocs.io
Project-URL: Source, https://github.com/simonsobs/LAT_MFLike
Project-URL: Tracker, https://github.com/simonsobs/LAT_MFLike/issues
Project-URL: Licensing, https://github.com/simonsobs/LAT_MFLike/blob/master/LICENCE
Keywords: likelihood,SO LAT,cosmology
Classifier: Development Status :: 2 - Pre-Alpha
Classifier: Intended Audience :: Developers
Classifier: License :: OSI Approved :: BSD License
Classifier: Natural Language :: English
Classifier: Programming Language :: Python :: 3.9
Classifier: Programming Language :: Python :: 3.10
Classifier: Programming Language :: Python :: 3.11
Classifier: Programming Language :: Python :: 3.12
Requires-Python: >=3.9.0
License-File: LICENSE
Requires-Dist: fgspectra>=1.3.0
Requires-Dist: syslibrary>=0.2.0
Requires-Dist: cobaya>=3.5.4
Requires-Dist: sacc>=0.9.0
Provides-Extra: test
Requires-Dist: pytest; extra == "test"
Requires-Dist: pytest-cov; extra == "test"
Requires-Dist: camb; extra == "test"
Requires-Dist: healpy; extra == "test"
Provides-Extra: notebook
Requires-Dist: jupyter; extra == "notebook"
Requires-Dist: camb; extra == "notebook"
Requires-Dist: seaborn; extra == "notebook"
Requires-Dist: latex2mathml; extra == "notebook"
Dynamic: license-file
